codeclean/__init__.py
codeclean/__main__.py
codeclean-1.0.1.dist-info/LICENSE
codeclean-1.0.1.dist-info/METADATA
codeclean-1.0.1.dist-info/WHEEL
codeclean-1.0.1.dist-info/top_level.txt
codeclean-1.0.1.dist-info/RECORD
