Metadata-Version: 2.1
Name: codeclean
Version: 1.0.1
Summary: Remove comments and docstrings from Python code.
Home-page: https://github.com/Ruu3f/cleancode
Author: Ruu3f
License: GPLv2
Project-URL: Source, https://github.com/Ruu3f/cleancode
Project-URL: Discord, https://discord.gg/XH6pUGkwRr
Keywords: clean,code,cleaner,comments,docstrings
Classifier: Development Status :: 5 - Production/Stable
Classifier: Intended Audience :: Developers
Classifier: License :: OSI Approved :: GNU General Public License v2 (GPLv2)
Classifier: Natural Language :: English
Classifier: Programming Language :: Python :: 3
Classifier: Programming Language :: Python :: Implementation :: CPython
Classifier: Programming Language :: Python :: Implementation :: PyPy
Requires-Python: >=3
License-File: LICENSE
